[{
  "_id": {
    "$oid": "6842d555c7942a901cb3a253"
  },
  "name": "Mercedes Vito",
  "pricingScore": {
    "$numberLong": "5"
  },
  "fixedCost": 2450,
  "imageUrl": "https://res.cloudinary.com/djzzikcey/image/upload/v1749821236/momtur_uploads/hnlnitnoslmfbbnzthaz.webp",
  "passengerCapacity": {
    "$numberLong": "7"
  },
  "luggageCapacity": {
    "$numberLong": "5"
  },
  "type": "Standart Minivan",
  "description": "Otomatik vites, rahat koltuk dizaynı, yüksek tavanlı, klimalı, USB portlu konforlu minivan.",
  "features": [
    "Otomatik vites",
    "Rahat koltuk dizaynı",
    "Yüksek tavan",
    "Klima",
    "USB port"
  ],
  "isAvailable": true,
  "createdAt": {
    "$date": "2025-06-06T11:47:33.508Z"
  },
  "updatedAt": {
    "$date": "2025-06-17T10:01:19.872Z"
  },
  "slug": "mercedes_vito"
},
{
  "_id": {
    "$oid": "6842d555c7942a901cb3a254"
  },
  "name": "Mercedes VIP Vito",
  "pricingScore": {
    "$numberLong": "8"
  },
  "fixedCost": 2450,
  "imageUrl": "https://res.cloudinary.com/djzzikcey/image/upload/v1749822077/momtur_uploads/j3yzwxutuspl2fa5duhe.webp",
  "passengerCapacity": {
    "$numberLong": "6"
  },
  "luggageCapacity": {
    "$numberLong": "6"
  },
  "type": "VIP Minivan",
  "description": "Lüks iç tasarım, VIP konforu, klimalı, USB portlu, amfi alanlı geniş minivan.",
  "features": [
    "Lüks iç tasarım",
    "VIP konforu",
    "Klima",
    "USB port",
    "Amfi alan"
  ],
  "isAvailable": true,
  "createdAt": {
    "$date": "2025-06-06T11:47:33.786Z"
  },
  "updatedAt": {
    "$date": "2025-06-17T10:02:18.591Z"
  },
  "slug": "mercedes_vip_vito"
},
{
  "_id": {
    "$oid": "6842d556c7942a901cb3a255"
  },
  "name": "Mercedes E-Class",
  "pricingScore": {
    "$numberLong": "7"
  },
  "fixedCost": 11000,
  "imageUrl": "https://res.cloudinary.com/djzzikcey/image/upload/v1749822305/momtur_uploads/vljel1ugwlv3dzxt5rnp.webp",
  "passengerCapacity": {
    "$numberLong": "3"
  },
  "luggageCapacity": {
    "$numberLong": "3"
  },
  "type": "Sedan",
  "description": "Lüks iç tasarım, multimedya sistemi, klimalı, USB portlu, konfor sürüşlü sedan.",
  "features": [
    "Lüks iç tasarım",
    "Multimedya sistemi",
    "Klima",
    "USB port",
    "Konfor sürüş"
  ],
  "isAvailable": true,
  "createdAt": {
    "$date": "2025-06-06T11:47:34.036Z"
  },
  "updatedAt": {
    "$date": "2025-06-17T10:03:18.562Z"
  },
  "slug": "mercedes_e_class"
},
{
  "_id": {
    "$oid": "6842d556c7942a901cb3a256"
  },
  "name": "Mercedes Sprinter",
  "pricingScore": {
    "$numberLong": "6"
  },
  "fixedCost": 5000,
  "imageUrl": "https://res.cloudinary.com/djzzikcey/image/upload/v1749822101/momtur_uploads/e5qsftazmdupeh8rri33.webp",
  "passengerCapacity": {
    "$numberLong": "16"
  },
  "luggageCapacity": {
    "$numberLong": "12"
  },
  "type": "Minibüs",
  "description": "Geniş iç hacim, yüksek tavan, klimalı, USB portlu, büyük bagaj alanlı minibüs.",
  "features": [
    "Geniş iç hacim",
    "Yüksek tavan",
    "Klima",
    "USB port",
    "Bagaj alanı"
  ],
  "isAvailable": true,
  "createdAt": {
    "$date": "2025-06-06T11:47:34.285Z"
  },
  "updatedAt": {
    "$date": "2025-06-17T10:03:39.556Z"
  },
  "slug": "mercedes_sprinter"
},
{
  "_id": {
    "$oid": "6842d556c7942a901cb3a257"
  },
  "name": "Mercedes S-Class",
  "pricingScore": {
    "$numberLong": "10"
  },
  "fixedCost": 18000,
  "imageUrl": "https://res.cloudinary.com/djzzikcey/image/upload/v1749822331/momtur_uploads/i0zihrirr6qxv4wjvpkb.webp",
  "passengerCapacity": {
    "$numberLong": "2"
  },
  "luggageCapacity": {
    "$numberLong": "3"
  },
  "type": "Sedan",
  "description": "En üst düzey lüks, gelişmiş güvenlik sistemleri, klimalı, USB portlu, konforlu yolculuk.",
  "features": [
    "En üst düzey lüks",
    "Gelişmiş güvenlik sistemleri",
    "Klima",
    "USB port",
    "Konforlu yolculuk"
  ],
  "isAvailable": true,
  "createdAt": {
    "$date": "2025-06-06T11:47:34.583Z"
  },
  "updatedAt": {
    "$date": "2025-06-17T10:04:12.072Z"
  },
  "slug": "mercedes_s_class"
},
{
  "_id": {
    "$oid": "6842d556c7942a901cb3a258"
  },
  "name": "Sultan Midibüs",
  "pricingScore": {
    "$numberLong": "4"
  },
  "fixedCost": 12000,
  "imageUrl": "https://res.cloudinary.com/djzzikcey/image/upload/v1749822400/momtur_uploads/fb8i1lkwzjhommkutrl6.jpg",
  "passengerCapacity": {
    "$numberLong": "31"
  },
  "luggageCapacity": {
    "$numberLong": "24"
  },
  "type": "Midibüs",
  "description": "Grup taşımacılığı için ideal, klimalı, USB portlu, rahat koltuklu, büyük bagaj alanlı midibüs.",
  "features": [
    "Grup taşımacılığı için ideal",
    "Klima",
    "USB port",
    "Rahat koltuklar",
    "Büyük bagaj alanı"
  ],
  "isAvailable": true,
  "createdAt": {
    "$date": "2025-06-06T11:47:34.868Z"
  },
  "updatedAt": {
    "$date": "2025-06-17T10:05:01.543Z"
  },
  "slug": "sultan_midibus"
},
{
  "_id": {
    "$oid": "6842d557c7942a901cb3a259"
  },
  "name": "Mercedes Travego",
  "pricingScore": {
    "$numberLong": "6"
  },
  "fixedCost": 18000,
  "imageUrl": "https://res.cloudinary.com/djzzikcey/image/upload/v1749822472/momtur_uploads/gvpfr6y9mg8nxevpfkat.jpg",
  "passengerCapacity": {
    "$numberLong": "46"
  },
  "luggageCapacity": {
    "$numberLong": "14"
  },
  "type": "Otobüs",
  "description": "Uzun mesafe için lüks otobüs, klimalı, USB portlu, yüksek konforlu, büyük bagaj alanlı.",
  "features": [
    "Uzun mesafe için lüks otobüs",
    "Klima",
    "USB port",
    "Yüksek konfor",
    "Büyük bagaj alanı"
  ],
  "isAvailable": true,
  "createdAt": {
    "$date": "2025-06-06T11:47:35.418Z"
  },
  "updatedAt": {
    "$date": "2025-06-17T10:05:26.084Z"
  },
  "slug": "mercedes_travego"
}]